mesil/__init__.py
mesil/cli.py
mesil/default.mplstyle
mesil/plot/customize.py
mesil/plot/plot.py
mesil/plot/plotters.py
mesil/process/analysis.py
mesil/process/clean.py
mesil/process/datafile.py
mesil/process/read.py
mesil/process/transform.py
mesil/tests/data/test_clean.py
mesil/tests/data/test_datafile.py
mesil/tests/data/test_read.py
mesil/tests/data/test_transform.py
mesil-0.1.0.dist-info/entry_points.txt
mesil-0.1.0.dist-info/LICENSE
mesil-0.1.0.dist-info/METADATA
mesil-0.1.0.dist-info/WHEEL
mesil-0.1.0.dist-info/RECORD
