Metadata-Version: 2.1
Name: mesil
Version: 0.1.0
Summary: Process and plot scientific data from various analyses (equipment specific)
License: MIT
Author: Daniel Levita
Author-email: 71600818+danplevs@users.noreply.github.com
Requires-Python: >=3.11,<4.0
Classifier: License :: OSI Approved :: MIT License
Classifier: Programming Language :: Python :: 3
Classifier: Programming Language :: Python :: 3.11
Requires-Dist: charset-normalizer (>=3.1.0,<4.0.0)
Requires-Dist: matplotlib (>=3.6.2,<4.0.0)
Requires-Dist: numpy (>=1.23.4,<2.0.0)
Requires-Dist: openpyxl (>=3.0.10,<4.0.0)
Requires-Dist: pandas (>=1.5.1,<2.0.0)
Requires-Dist: typer[all] (>=0.9.0,<0.10.0)
Requires-Dist: xlrd (>=2.0.1,<3.0.0)
